mystucoke/__init__.py
mystucoke/tcpclientcorrespondence.py
mystucoke/tcpservercorrespondence.py
mystucoke-0.2.5.dist-info/LICENSE
mystucoke-0.2.5.dist-info/METADATA
mystucoke-0.2.5.dist-info/WHEEL
mystucoke-0.2.5.dist-info/top_level.txt
mystucoke-0.2.5.dist-info/RECORD
