Metadata-Version: 2.1
Name: mystucoke
Version: 0.2.5
Summary: A mystucoke project for STU
Home-page: https://github.com/yourusername/mystucoke
Author: Jack-Li
Author-email: 477434296@qq.com
Classifier: Programming Language :: Python :: 3
Classifier: License :: OSI Approved :: MIT License
Classifier: Operating System :: OS Independent
Requires-Python: >=3.6
License-File: LICENSE
